{
  "timestamp": "2026-06-09 12:43:46 UTC",
  "category": "changes",
  "data": {
    "count": 1,
    "changes": [
      {
        "type": "api_items_added",
        "endpoint": "/wp-json/wp/v2/posts",
        "count": 1,
        "items": [
          {
            "id": 2952,
            "title": "STRUCTURAL ANALYSIS",
            "modified": "2026-06-09T13:35:24",
            "type": "post",
            "status": "publish",
            "link": "https://project-skyscraper.com/2026/06/09/structural-analysis-133722/",
            "author": 279180095,
            "name": "",
            "date_gmt": "2026-06-09T12:37:00",
            "post_parent": 0,
            "parent": 0,
            "categories": [
              6325
            ],
            "tags": []
          }
        ],
        "detail": "1 new item(s) in /wp-json/wp/v2/posts"
      }
    ]
  }
}
